{
  "search": "यहाँ खोजें...",
  "level": "लेवल 3",

  "welcome": "स्वागत है!",
  "loginSub": "अपने सीखने की यात्रा शुरू करने के लिए लॉगिन करें",
  "userId": "यूज़र आईडी",
  "emailAddress": "ईमेल पता",
  "password": "पासवर्ड",
  "forgot": "पासवर्ड भूल गए?",
  "signIn": "लॉगिन करें",
  "orContinue": "या इनसे लॉगिन करें",
  "noAccount": "खाता नहीं है?",
  "signUp": "साइन अप करें",

  "greeting": "नमस्ते, संदीप! 👋",
  "greetingSub": "आज कुछ नया सीखते हैं।",
  "dayStreak": "दिन की स्ट्रीक",
  "novice": "नॉविस इंजीनियर",

  "continueLearning": "जारी रखें",
  "lesson03": "पाठ 03",
  "ohmsLaw": "ओम का नियम",
  "basicElec": "बेसिक इलेक्ट्रॉनिक्स",
  "complete": "पूर्ण",
  "resumeLesson": "पाठ जारी रखें",
  "lessonInfo": "पाठ जानकारी",

  "sparkTitle": "स्पार्क AI असिस्टेंट",
  "sparkMsg": "ओम के नियम या किसी भी इलेक्ट्रॉनिक्स अवधारणा में मदद चाहिए? मैं यहाँ मदद के लिए हूँ!",
  "askPlaceholder": "इलेक्ट्रॉनिक्स के बारे में कुछ भी पूछें...",
  "chipOhm": "ओम का नियम",
  "chipSeries": "सीरीज़ vs पैरलल",
  "chipVoltage": "वोल्टेज क्या है?",

  "progressGauge": "प्रगति (प्रोग्रेस गेज)",
  "overallProgress": "कुल प्रगति",
  "lessonsCompleted": "पाठ पूरे",
  "quizzesPassed": "क्विज़ पूरे",
  "timeLearned": "समय सीखा",

  "courseLibrary": "कोर्स लाइब्रेरी",
  "viewAll": "सभी देखें",
  "activityTimeline": "गतिविधि",
  "viewFullActivity": "सभी गतिविधियाँ देखें",
  "achievementsLabel": "उपलब्धियां",
  "weeklyGoal": "साप्ताहिक लक्ष्य",
  "lessons": "पाठ",
  "doingGreat": "आप बहुत अच्छा कर रहे हैं! 🚀",
  "viewGoals": "लक्ष्य देखें",

  "lessonContent": "पाठ सामग्री",
  "ohmFormula": "ओम का नियम सूत्र",
  "ohmBody": "ओम के नियम के अनुसार, किसी चालक में बहने वाली धारा उस पर लगे वोल्टेज के समानुपाती होती है।",
  "where": "जहाँ,",
  "vVolt": "V = वोल्टेज (वोल्ट)",
  "iCurr": "I = धारा (एम्पियर)",
  "rRes": "R = प्रतिरोध (ओम)",
  "askSpark": "स्पार्क AI से पूछें",
  "notesBtn": "नोट्स",
  "bookmark": "बुकमार्क",
  "prev": "पिछला",
  "next": "अगला",
  "takeQuiz": "क्विज़ लें",

  "quiz": "क्विज़",
  "quizName": "ओम का नियम क्विज़",
  "questionOf": "प्रश्न 2 / 10",
  "quizQ": "ओम के नियम का सही सूत्र क्या है?",
  "showExplanation": "व्याख्या देखें",
  "answered": "उत्तर दिया",
  "current": "वर्तमान",

  "greatJob": "शानदार! 🎉",
  "scoredOut": "आपने 10 में से 9 पास किया",
  "correct": "सही उत्तर",
  "incorrect": "गलत",
  "timeTaken": "समय लिया",
  "reviewAnswers": "उत्तर समीक्षा करें",
  "backToLesson": "पाठ पर वापस जाएं",
  "keepPracticing": "100% पाने के लिए अभ्यास जारी रखें!",

  "mcqReview": "उत्तर समीक्षा",
  "reviewQ": "प्रश्न 2. ओम के नियम का सही सूत्र क्या है?",
  "yourAnswer": "आपका उत्तर",
  "correctAnswer": "सही उत्तर",
  "explanation": "व्याख्या",
  "explBody": "ओम के नियम के अनुसार, वोल्टेज (V) धारा (I) और प्रतिरोध (R) के गुणनफल के बराबर होता है।",

  "myNotes": "मेरे नोट्स",
  "keyPoints": "मुख्य बिंदु",
  "addNote": "नया नोट जोड़ें",
  "saveNote": "नोट सहेजें",

  "sparkQ": "समझाएं कि प्रतिरोध सर्किट में वोल्टेज को कैसे प्रभावित करता है?",
  "sparkA": "बढ़िया सवाल! ओम के नियम (V = I × R) के अनुसार, यदि धारा स्थिर रहे और प्रतिरोध (R) बढ़े, तो कंपोनेंट पर वोल्टेज (V) भी बढ़ जाता है। प्रतिरोध धारा के प्रवाह का विरोध करता है, जिससे वोल्टेज ड्रॉप बनता है। क्या आप एक उदाहरण देखना चाहेंगे?",

  "continueLessonTitle": "जारी रखें",
  "lessonProgress": "पाठ प्रगति",
  "continueBtn": "पाठ जारी रखें",

  "navHome": "होम",
  "navLessons": "कोर्स",
  "navSpark": "स्पार्क",
  "navQuiz": "क्विज़",
  "navNotes": "नोट्स",

  "courses": [
    { "key": "basic", "name": "बेसिक इलेक्ट्रॉनिक्स", "lessons": "12 / 28 पाठ", "pct": 43, "tag": "IC CHIP" },
    { "key": "analog", "name": "एनालॉग इलेक्ट्रॉनिक्स", "lessons": "8 / 24 पाठ", "pct": 33, "tag": "WAVEFORM" },
    { "key": "digital", "name": "डिजिटल इलेक्ट्रॉनिक्स", "lessons": "6 / 26 पाठ", "pct": 23, "tag": "1010 LOGIC" },
    { "key": "sensors", "name": "सेंसर और एक्चुएटर्स", "lessons": "2 / 18 पाठ", "pct": 11, "tag": "SENSOR" }
  ],
  "activities": [
    { "key": "completed", "icon": "check", "title": "पाठ 02 पूरा किया", "sub": "किरचॉफ वोल्टेज नियम", "time": "2 घं. पहले" },
    { "key": "quiz", "icon": "quiz", "title": "क्विज़ स्कोर: 90%", "sub": "ओम का नियम क्विज़", "time": "5 घं. पहले" },
    { "key": "started", "icon": "play", "title": "पाठ 03 शुरू किया", "sub": "ओम का नियम", "time": "कल" }
  ],
  "achievements": [
    { "key": "ohms-expert", "icon": "ohm", "title": "ओम एक्सपर्ट", "sub": "ओम क्विज़ में 90% स्कोर करें" },
    { "key": "consistent-learner", "icon": "calendar", "title": "निरंतर सीखने वाला", "sub": "7 दिन की स्ट्रीक बनाए रखें" },
    { "key": "circuit-explorer", "icon": "hex", "title": "सर्किट एक्सप्लोरर", "sub": "10 पाठ पूरे करें" }
  ],
  "lessonSteps": [
    { "n": 1, "label": "परिचय" },
    { "n": 2, "label": "प्रतिरोध क्या है?" },
    { "n": 3, "label": "ओम का नियम सूत्र", "cur": true },
    { "n": 4, "label": "रियल लाइफ उदाहरण" },
    { "n": 5, "label": "हल किए उदाहरण" },
    { "n": 6, "label": "सारांश" }
  ],
  "lessonTabLabels": ["पाठ", "व्याख्या", "सिमुलेशन", "नोट्स"],
  "quizOptions": ["V = I / R", "V = I × R", "R = V − I", "I = V ÷ R"],
  "notesList": [
    { "title": "ओम का नियम", "cur": true },
    { "title": "किरचॉफ के नियम" },
    { "title": "सीरीज़ सर्किट" },
    { "title": "पैरलल सर्किट" }
  ],
  "notesBody": [
    "वोल्टेज धारा के समानुपाती होता है।",
    "किसी चालक के लिए प्रतिरोध स्थिर रहता है।",
    "इकाइयाँ: V (वोल्ट), I (एम्पियर), R (ओम)।"
  ],
  "reviewLabels": ["प्र1", "प्र2", "प्र3", "प्र4", "प्र5", "प्र6"],
  "progressSteps": [
    { "label": "परिचय", "done": true },
    { "label": "प्रतिरोध क्या है?", "done": true },
    { "label": "ओम का नियम सूत्र", "cur": true },
    { "label": "रियल लाइफ उदाहरण" },
    { "label": "हल किए उदाहरण" }
  ]
}
